LICENSE
README.md
setup.cfg
setup.py
wulthm/__init__.py
wulthm/wulthm.py
wulthm.egg-info/PKG-INFO
wulthm.egg-info/SOURCES.txt
wulthm.egg-info/dependency_links.txt
wulthm.egg-info/top_level.txt