Metadata-Version: 2.1
Name: wulthm
Version: 1.3
Summary: Сollection of algorithms in Python module
Home-page: https://github.com/wultes/wulthm
Author: Kirill Melnikov @wultes
License: MIT
License-File: LICENSE
